tqs.py
tqs_client-0.7.1.dist-info/LICENSE.txt
tqs_client-0.7.1.dist-info/METADATA
tqs_client-0.7.1.dist-info/RECORD
tqs_client-0.7.1.dist-info/WHEEL
tqs_client-0.7.1.dist-info/metadata.json
tqs_client-0.7.1.dist-info/top_level.txt
