Metadata-Version: 2.0
Name: tqs-client
Version: 0.7.1
Summary: Tiny Queue Service Client
Home-page: https://github.com/st3fan/tqs-client
Author: Stefan Arentz
Author-email: stefan@arentz.ca
Requires-Python: >=3
License-File: LICENSE
Requires-Dist: requests
